parea/__about__.py
parea/__init__.py
parea/main.py
parea-0.1.1.dist-info/LICENSE
parea-0.1.1.dist-info/METADATA
parea-0.1.1.dist-info/WHEEL
parea-0.1.1.dist-info/entry_points.txt
parea-0.1.1.dist-info/top_level.txt
parea-0.1.1.dist-info/RECORD
