Metadata-Version: 2.1
Name: parea
Version: 0.1.1
Summary: The easiest way to calculate the projected/frontal area of an STL.
Home-page: https://github.com/nathanrooy/p-area
Author: Nathan A. Rooy
Author-email: nathanrooy@gmail.com
License: UNKNOWN
Platform: UNKNOWN
Classifier: Programming Language :: Python :: 3
Classifier: License :: OSI Approved :: MIT License
Classifier: Operating System :: OS Independent
Requires-Python: >=3.5
Requires-Dist: shapely
Requires-Dist: numpy
